polars_readlines-0.2.1.dist-info/METADATA
polars_readlines-0.2.1.dist-info/WHEEL
polars_readlines/__init__.py
polars_readlines/_polars_readlines.abi3.so
polars_readlines-0.2.1.dist-info/RECORD
